simple_math/simple_math.py
simple_math/__init__.py
simple_math-1.1.0.dist-info/top_level.txt
simple_math-1.1.0.dist-info/METADATA
simple_math-1.1.0.dist-info/DESCRIPTION.rst
simple_math-1.1.0.dist-info/metadata.json
simple_math-1.1.0.dist-info/WHEEL
simple_math-1.1.0.dist-info/RECORD
