Metadata-Version: 2.0
Name: simple-math
Version: 1.1.0
Summary: some usefull math functions
Home-page: https://pypi.python.org/pypi/simple_math/1.1.0
Author: Noah
Author-email: noahmouse2011@gmail.com
License: GPL
Platform: UNKNOWN
Classifier: Development Status :: 3 - Alpha
Classifier: Intended Audience :: Developers
Classifier: Operating System :: OS Independent
Classifier: Natural Language :: English
Classifier: Programming Language :: Python :: 2
Classifier: Programming Language :: Python :: 3
Classifier: License :: OSI Approved :: GNU General Public License v2 or later (GPLv2+)
